{"scene_id":4010,"activity_id":null,"name":"動物園-第四區_上架","thumbnail":null,"ar_objects":[{"id":70620,"name":"體驗結束_v2_png","location":{"y":-0.86124,"rotate_y":-90.0,"z":2.23786,"x":13.13278,"rotate_x":0.0,"rotate_z":0.0},"zoom":{"x":5.9322,"y":5.9322,"z":5.9322},"configuration":null,"created_at":"2025-11-24T01:08:21.798+08:00","updated_at":"2025-11-24T01:19:32.104+08:00","light_id":null,"ar_object_owner_id":null,"ar_object_owner_type":null,"model":{"type":5,"fields":{"width":1.0,"height":1.0,"face_me":false,"is_ignore":false,"visible_distance":6.0,"is_hidden":false,"is_size_scale_lock":true,"is_allow_pinch":false,"is_double_sided":true,"is_occlusion":false,"bloom_intensity":0.0,"bloom_radius":0.0},"texture":{"url":"https://assets.lig.com.tw/ar_asset/8sg7d3wb09ijqsayk3nalg4cg0n8.png","id":"28163","content_type":"image/png","file_path":"8s/8sg7d3wb09ijqsayk3nalg4cg0n8.png"},"ios_texture":{"content_type":"image/png"},"android_texture":{"content_type":"image/png"}},"actions":null,"transparency":1.0,"group":1,"zone_id":null,"events":[],"scene_id":4010,"sub_events":null,"is_child":false},{"id":70619,"name":"第四區-向前走_水獺-R_glb_glb","location":{"y":-1.30266,"rotate_y":-90.0,"z":2.23786,"x":9.3403,"rotate_x":0.0,"rotate_z":0.0},"zoom":{"x":0.032,"y":0.032,"z":0.032},"configuration":null,"created_at":"2025-11-24T01:07:42.696+08:00","updated_at":"2025-11-24T01:19:32.021+08:00","light_id":null,"ar_object_owner_id":null,"ar_object_owner_type":null,"model":{"type":8,"fields":{"visible_distance":3.0,"is_metal":false,"is_hidden":false,"is_allow_pinch":false,"width":1,"height":1,"face_me":false,"is_ignore":false,"is_double_sided":false,"multiply_is_zero_y":false,"is_occlusion":false},"texture":null,"ios_texture":{"url":"https://assets.lig.com.tw/ar_asset/ovekggjcg6mwc5ijp8ngll58xfp6.glb","id":"28818","file_path":"ov/ovekggjcg6mwc5ijp8ngll58xfp6.glb"},"android_texture":{"url":"https://assets.lig.com.tw/ar_asset/ovekggjcg6mwc5ijp8ngll58xfp6.glb","id":"28818","file_path":"ov/ovekggjcg6mwc5ijp8ngll58xfp6.glb"}},"actions":null,"transparency":1.0,"group":1,"zone_id":null,"events":[],"scene_id":4010,"sub_events":null,"is_child":false},{"id":69509,"name":"導覽員第三層-通用","location":{"y":-0.58725,"rotate_y":0.0,"z":0.6,"x":0.0,"rotate_x":0.0,"rotate_z":0.0},"zoom":{"x":1.0,"y":1.0,"z":1.0},"configuration":null,"created_at":"2025-11-02T17:22:46.868+08:00","updated_at":"2025-11-24T01:19:27.591+08:00","light_id":null,"ar_object_owner_id":null,"ar_object_owner_type":null,"model":{"type":5,"fields":{"width":1.0,"height":1.0,"face_me":false,"is_ignore":false,"visible_distance":20.0,"is_hidden":false,"is_size_scale_lock":true,"is_child":false,"is_allow_pinch":false,"is_allow_rotate":false,"is_double_sided":false,"is_occlusion":false,"bloom_intensity":0.0,"bloom_radius":0.0},"texture":{"url":"https://assets.lig.com.tw/ar_asset/3qacvd1ohyoghactmn6pmpox35u2.png","id":"28381","content_type":"image/png","file_path":"3q/3qacvd1ohyoghactmn6pmpox35u2.png"},"ios_texture":{"content_type":"image/png"},"android_texture":{"content_type":"image/png"}},"actions":null,"transparency":0.0,"group":1,"zone_id":42,"events":[{"id":1,"values":{},"actions":[{"id":19,"values":{"group":1,"transparency":0.0,"delay_time":0.0,"time":0.10000000149011612}},{"id":19,"values":{"group":1,"transparency":1.0,"obj_id":69148,"delay_time":0.0,"time":0.10000000149011612}},{"id":19,"values":{"group":1,"transparency":1.0,"obj_id":69149,"delay_time":0.0,"time":0.10000000149011612}},{"id":19,"values":{"group":1,"transparency":1.0,"obj_id":69150,"delay_time":0.0,"time":0.10000000149011612}}]}],"scene_id":4010,"sub_events":{},"is_child":false},{"id":69499,"name":"問答-水獺-x","location":{"y":-0.2,"rotate_y":-254.8758,"z":8.58559,"x":-14.04123,"rotate_x":0.0,"rotate_z":0.0},"zoom":{"x":3.0,"y":3.0,"z":3.0},"configuration":null,"created_at":"2025-11-02T16:32:13.210+08:00","updated_at":"2025-11-24T01:19:27.866+08:00","light_id":null,"ar_object_owner_id":null,"ar_object_owner_type":null,"model":{"type":5,"fields":{"width":1.0,"height":1.0,"face_me":false,"is_ignore":false,"visible_distance":20.0,"is_hidden":false,"is_size_scale_lock":true,"is_child":false,"is_allow_pinch":false,"is_allow_rotate":false,"is_double_sided":false,"is_occlusion":false,"bloom_intensity":0.0,"bloom_radius":0.0},"texture":{"url":"https://assets.lig.com.tw/ar_asset/jn0swqohuyqimltjelthpibl0lxa.png","id":"28483","content_type":"image/png","file_path":"jn/jn0swqohuyqimltjelthpibl0lxa.png"},"ios_texture":{"content_type":"image/png"},"android_texture":{"content_type":"image/png"}},"actions":null,"transparency":0.0,"group":1,"zone_id":42,"events":[],"scene_id":4010,"sub_events":{},"is_child":false},{"id":69498,"name":"問答-水獺-o","location":{"y":-0.2,"rotate_y":-254.8758,"z":8.58081,"x":-14.04254,"rotate_x":0.0,"rotate_z":0.0},"zoom":{"x":3.0,"y":3.0,"z":3.0},"configuration":null,"created_at":"2025-11-02T16:32:13.166+08:00","updated_at":"2025-11-24T01:19:27.524+08:00","light_id":null,"ar_object_owner_id":null,"ar_object_owner_type":null,"model":{"type":5,"fields":{"width":1.0,"height":1.0,"face_me":false,"is_ignore":false,"visible_distance":20.0,"is_hidden":false,"is_size_scale_lock":true,"is_child":false,"is_allow_pinch":false,"is_allow_rotate":false,"is_double_sided":false,"is_occlusion":false,"bloom_intensity":0.0,"bloom_radius":0.0},"texture":{"url":"https://assets.lig.com.tw/ar_asset/4xx9ss06nrssozrdditwyzy1bffw.png","id":"28484","content_type":"image/png","file_path":"4x/4xx9ss06nrssozrdditwyzy1bffw.png"},"ios_texture":{"content_type":"image/png"},"android_texture":{"content_type":"image/png"}},"actions":null,"transparency":0.0,"group":1,"zone_id":42,"events":[],"scene_id":4010,"sub_events":{},"is_child":false},{"id":69497,"name":"答錯音效","location":{"x":-13.83243,"y":9.6,"z":5.43504,"rotate_x":0.0,"rotate_y":-90.2023,"rotate_z":-0.0},"zoom":{"x":1.0,"y":1.0,"z":1.0},"configuration":null,"created_at":"2025-11-02T16:32:13.130+08:00","updated_at":"2025-11-13T19:33:50.962+08:00","light_id":null,"ar_object_owner_id":null,"ar_object_owner_type":null,"model":{"type":9,"fields":{"face_me":false,"is_ignore":true,"visible_distance":20.0,"hue_range":20.0,"saturation":0.5,"is_play":false,"is_hidden":false,"is_loop_play":false,"is_allow_pinch":false,"hue_angle":null,"is_double_sided":false,"is_occlusion":false},"texture":{"url":"https://assets.lig.com.tw/ar_asset/fv2jgiwt1hbad9sx6frsystxch8x.mp4","id":"28389","file_path":"fv/fv2jgiwt1hbad9sx6frsystxch8x.mp4"},"ios_texture":{},"android_texture":{}},"actions":null,"transparency":0.0,"group":1,"zone_id":42,"events":[],"scene_id":4010,"sub_events":{},"is_child":false},{"id":69496,"name":"拍片用音效_答對了_","location":{"x":-13.83243,"y":9.6,"z":5.43504,"rotate_x":0.0,"rotate_y":-90.2023,"rotate_z":-0.0},"zoom":{"x":1.0,"y":1.0,"z":1.0},"configuration":null,"created_at":"2025-11-02T16:32:13.093+08:00","updated_at":"2025-11-13T19:33:50.846+08:00","light_id":null,"ar_object_owner_id":null,"ar_object_owner_type":null,"model":{"type":9,"fields":{"face_me":false,"is_ignore":true,"visible_distance":20.0,"hue_range":20.0,"saturation":0.5,"is_play":false,"is_hidden":false,"is_loop_play":false,"is_allow_pinch":false,"hue_angle":null,"is_double_sided":false,"is_occlusion":false},"texture":{"url":"https://assets.lig.com.tw/ar_asset/010viw6yxesesr10yd7dhkdiw6k4.mp4","id":"28390","file_path":"01/010viw6yxesesr10yd7dhkdiw6k4.mp4"},"ios_texture":{},"android_texture":{}},"actions":null,"transparency":0.0,"group":1,"zone_id":42,"events":[],"scene_id":4010,"sub_events":{},"is_child":false},{"id":69495,"name":"觸發問答-錯誤","location":{"y":-0.86,"rotate_y":-74.8747,"z":8.58559,"x":-14.04123,"rotate_x":0.0,"rotate_z":0.0},"zoom":{"x":0.95,"y":0.16,"z":0.02},"configuration":null,"created_at":"2025-11-02T16:32:13.050+08:00","updated_at":"2025-11-24T01:19:27.805+08:00","light_id":null,"ar_object_owner_id":null,"ar_object_owner_type":null,"model":{"type":8,"fields":{"visible_distance":20.0,"is_metal":false,"is_hidden":false,"is_allow_pinch":false,"width":1,"height":1,"face_me":false,"is_ignore":false,"is_double_sided":false,"animation_speed":null,"start_frame":null,"end_frame":null,"fps":null,"multiply_number":null,"multiply_radius":null,"multiply_range":null,"multiply_is_zero_y":false,"is_occlusion":false},"texture":null,"ios_texture":{"url":"https://assets.lig.com.tw/ar_asset/7k0l223dlvkjqix756i1k9ser522.glb","id":"28391","file_path":"7k/7k0l223dlvkjqix756i1k9ser522.glb"},"android_texture":{"url":"https://assets.lig.com.tw/ar_asset/7k0l223dlvkjqix756i1k9ser522.glb","id":"28391","file_path":"7k/7k0l223dlvkjqix756i1k9ser522.glb"}},"actions":null,"transparency":1.0,"group":1,"zone_id":42,"events":[{"id":1,"values":{},"actions":[{"id":35,"values":{"group":1,"obj_id":69495,"delay_time":0.0}},{"id":35,"values":{"group":1,"obj_id":69494,"delay_time":0.0}},{"id":19,"values":{"group":1,"transparency":0.0,"obj_id":69492,"delay_time":0.0,"time":0.10000000149011612}},{"id":6,"values":{"group":2,"obj_id":69495,"delay_time":0.0}},{"id":19,"values":{"group":2,"transparency":1.0,"obj_id":69499,"delay_time":0.0,"time":0.10000000149011612}},{"id":19,"values":{"group":3,"transparency":1.0,"delay_time":0.0,"time":2.0}},{"id":19,"values":{"group":4,"transparency":0.0,"obj_id":69499,"delay_time":0.0,"time":0.10000000149011612}},{"id":19,"values":{"group":5,"transparency":1.0,"obj_id":69493,"delay_time":0.0,"time":0.10000000149011612}},{"id":24,"values":{"impact_feedback_style":0,"group":5,"delay_time":0.0}}]}],"scene_id":4010,"sub_events":{},"is_child":false},{"id":69494,"name":"觸發問答-正確","location":{"y":-0.49,"rotate_y":-74.8747,"z":8.58559,"x":-14.04123,"rotate_x":0.0,"rotate_z":0.0},"zoom":{"x":0.95,"y":0.16,"z":0.02},"configuration":null,"created_at":"2025-11-02T16:32:12.992+08:00","updated_at":"2025-11-24T01:19:27.672+08:00","light_id":null,"ar_object_owner_id":null,"ar_object_owner_type":null,"model":{"type":8,"fields":{"visible_distance":20.0,"is_metal":false,"is_hidden":false,"is_allow_pinch":false,"width":1,"height":1,"face_me":false,"is_ignore":false,"is_double_sided":false,"animation_speed":null,"start_frame":null,"end_frame":null,"fps":null,"multiply_number":null,"multiply_radius":null,"multiply_range":null,"multiply_is_zero_y":false,"is_occlusion":false},"texture":null,"ios_texture":{"url":"https://assets.lig.com.tw/ar_asset/7k0l223dlvkjqix756i1k9ser522.glb","id":"28391","file_path":"7k/7k0l223dlvkjqix756i1k9ser522.glb"},"android_texture":{"url":"https://assets.lig.com.tw/ar_asset/7k0l223dlvkjqix756i1k9ser522.glb","id":"28391","file_path":"7k/7k0l223dlvkjqix756i1k9ser522.glb"}},"actions":null,"transparency":1.0,"group":1,"zone_id":42,"events":[{"id":1,"values":{},"actions":[{"id":35,"values":{"group":1,"obj_id":69495,"delay_time":0.0}},{"id":35,"values":{"group":1,"obj_id":69494,"delay_time":0.0}},{"id":19,"values":{"group":1,"transparency":0.0,"obj_id":69492,"delay_time":0.0,"time":0.10000000149011612}},{"id":6,"values":{"group":2,"obj_id":69496,"delay_time":0.0}},{"id":19,"values":{"group":2,"transparency":1.0,"obj_id":69498,"delay_time":0.0,"time":0.10000000149011612}},{"id":19,"values":{"group":3,"transparency":1.0,"delay_time":0.0,"time":2.0}},{"id":19,"values":{"group":4,"transparency":0.0,"obj_id":69498,"delay_time":0.0,"time":0.10000000149011612}},{"id":19,"values":{"group":5,"transparency":1.0,"obj_id":69493,"delay_time":0.0,"time":0.10000000149011612}},{"id":24,"values":{"impact_feedback_style":0,"group":5,"delay_time":0.0}}]}],"scene_id":4010,"sub_events":{},"is_child":false},{"id":69493,"name":"本區結束_v2","location":{"y":-0.00713,"rotate_y":-254.1237,"z":8.53862,"x":-15.36322,"rotate_x":0.0,"rotate_z":0.0},"zoom":{"x":5.756,"y":5.756,"z":5.756},"configuration":null,"created_at":"2025-11-02T16:32:12.917+08:00","updated_at":"2025-11-24T01:19:28.436+08:00","light_id":null,"ar_object_owner_id":null,"ar_object_owner_type":null,"model":{"type":5,"fields":{"width":1.0,"height":1.0,"face_me":false,"is_ignore":false,"visible_distance":6.0,"is_hidden":false,"is_size_scale_lock":true,"is_allow_pinch":false,"is_double_sided":true,"is_occlusion":false,"bloom_intensity":0.0,"bloom_radius":0.0},"texture":{"url":"https://assets.lig.com.tw/ar_asset/f4fonqwxqmr3iamk1r1nntwys54s.png","id":"28392","content_type":"image/png","file_path":"f4/f4fonqwxqmr3iamk1r1nntwys54s.png"},"ios_texture":{"content_type":"image/png"},"android_texture":{"content_type":"image/png"}},"actions":null,"transparency":1.0,"group":1,"zone_id":42,"events":[],"scene_id":4010,"sub_events":{},"is_child":false},{"id":69492,"name":"問答-水獺","location":{"y":-0.2,"rotate_y":-254.8758,"z":8.58559,"x":-14.04123,"rotate_x":0.0,"rotate_z":0.0},"zoom":{"x":3.0,"y":3.0,"z":3.0},"configuration":null,"created_at":"2025-11-02T16:32:12.811+08:00","updated_at":"2025-11-24T01:19:28.192+08:00","light_id":null,"ar_object_owner_id":null,"ar_object_owner_type":null,"model":{"type":5,"fields":{"width":1.0,"height":1.0,"face_me":false,"is_ignore":false,"visible_distance":5.0,"is_hidden":false,"is_size_scale_lock":true,"is_allow_pinch":false,"is_double_sided":true,"is_occlusion":false,"bloom_intensity":0.0,"bloom_radius":0.0},"texture":{"url":"https://assets.lig.com.tw/ar_asset/atfahkt6unrn4i5ea5eje93cxzu0.png","id":"28485","content_type":"image/png","file_path":"at/atfahkt6unrn4i5ea5eje93cxzu0.png"},"ios_texture":{"content_type":"image/png"},"android_texture":{"content_type":"image/png"}},"actions":null,"transparency":1.0,"group":1,"zone_id":42,"events":[],"scene_id":4010,"sub_events":{},"is_child":false},{"id":69381,"name":"第二區_腳印_一組","location":{"y":-2.0,"rotate_y":-272.0,"z":1.7,"x":2.7,"rotate_x":0.0,"rotate_z":0.0},"zoom":{"x":1.0,"y":1.0,"z":1.0},"configuration":null,"created_at":"2025-10-31T13:30:49.440+08:00","updated_at":"2025-11-13T19:33:51.572+08:00","light_id":null,"ar_object_owner_id":null,"ar_object_owner_type":null,"model":{"type":8,"fields":{"visible_distance":20.0,"is_metal":false,"is_hidden":false,"is_allow_pinch":false,"width":1,"height":1,"face_me":false,"is_ignore":false,"is_double_sided":false,"animation_speed":null,"start_frame":null,"end_frame":null,"fps":null,"multiply_number":null,"multiply_radius":null,"multiply_range":null,"multiply_is_zero_y":false,"is_occlusion":false},"texture":null,"ios_texture":{"url":"https://assets.lig.com.tw/ar_asset/wbkafbckuril7abqi82oljox8hfw.glb","id":"28382","file_path":"wb/wbkafbckuril7abqi82oljox8hfw.glb"},"android_texture":{"url":"https://assets.lig.com.tw/ar_asset/wbkafbckuril7abqi82oljox8hfw.glb","id":"28382","file_path":"wb/wbkafbckuril7abqi82oljox8hfw.glb"}},"actions":null,"transparency":1.0,"group":1,"zone_id":42,"events":[],"scene_id":4010,"sub_events":null,"is_child":false},{"id":69380,"name":"第二區_腳印_一組","location":{"y":-2.0,"rotate_y":-0.0,"z":4.3,"x":0.0,"rotate_x":0.0,"rotate_z":-0.0},"zoom":{"x":1.0,"y":1.0,"z":1.0},"configuration":null,"created_at":"2025-10-31T13:30:45.764+08:00","updated_at":"2025-11-13T19:33:51.689+08:00","light_id":null,"ar_object_owner_id":null,"ar_object_owner_type":null,"model":{"type":8,"fields":{"visible_distance":20.0,"is_metal":false,"is_hidden":false,"is_allow_pinch":false,"width":1,"height":1,"face_me":false,"is_ignore":false,"is_double_sided":false,"animation_speed":null,"start_frame":null,"end_frame":null,"fps":null,"multiply_number":null,"multiply_radius":null,"multiply_range":null,"multiply_is_zero_y":false,"is_occlusion":false},"texture":null,"ios_texture":{"url":"https://assets.lig.com.tw/ar_asset/wbkafbckuril7abqi82oljox8hfw.glb","id":"28382","file_path":"wb/wbkafbckuril7abqi82oljox8hfw.glb"},"android_texture":{"url":"https://assets.lig.com.tw/ar_asset/wbkafbckuril7abqi82oljox8hfw.glb","id":"28382","file_path":"wb/wbkafbckuril7abqi82oljox8hfw.glb"}},"actions":null,"transparency":1.0,"group":1,"zone_id":42,"events":[],"scene_id":4010,"sub_events":null,"is_child":false},{"id":69373,"name":"第四區-向前走_黑熊","location":{"y":-1.2,"rotate_y":0.0,"z":1.0,"x":2.0,"rotate_x":0.0,"rotate_z":-0.0},"zoom":{"x":0.032,"y":0.032,"z":0.032},"configuration":null,"created_at":"2025-10-31T13:28:52.604+08:00","updated_at":"2025-11-13T19:33:51.974+08:00","light_id":null,"ar_object_owner_id":null,"ar_object_owner_type":null,"model":{"type":8,"fields":{"visible_distance":20.0,"is_metal":false,"is_hidden":false,"is_allow_pinch":false,"width":1,"height":1,"face_me":false,"is_ignore":false,"is_double_sided":false,"animation_speed":null,"start_frame":null,"end_frame":null,"fps":null,"multiply_number":null,"multiply_radius":null,"multiply_range":null,"multiply_is_zero_y":false,"is_occlusion":false},"texture":null,"ios_texture":{"url":"https://assets.lig.com.tw/ar_asset/yyy3ktyti8jhp977infhrl5nlcdu.glb","id":"28486","file_path":"yy/yyy3ktyti8jhp977infhrl5nlcdu.glb"},"android_texture":{"url":"https://assets.lig.com.tw/ar_asset/yyy3ktyti8jhp977infhrl5nlcdu.glb","id":"28486","file_path":"yy/yyy3ktyti8jhp977infhrl5nlcdu.glb"}},"actions":null,"transparency":1.0,"group":1,"zone_id":42,"events":[],"scene_id":4010,"sub_events":null,"is_child":false},{"id":69372,"name":"第四區-向前走_水獺","location":{"y":-1.56795,"rotate_y":-90.0,"z":2.0,"x":-2.2,"rotate_x":0.0,"rotate_z":0.0},"zoom":{"x":0.032,"y":0.032,"z":0.032},"configuration":null,"created_at":"2025-10-31T13:28:49.846+08:00","updated_at":"2025-11-24T01:19:28.629+08:00","light_id":null,"ar_object_owner_id":null,"ar_object_owner_type":null,"model":{"type":8,"fields":{"visible_distance":20.0,"is_metal":false,"is_hidden":false,"is_allow_pinch":false,"width":1,"height":1,"face_me":false,"is_ignore":false,"is_double_sided":false,"animation_speed":null,"start_frame":null,"end_frame":null,"fps":null,"multiply_number":null,"multiply_radius":null,"multiply_range":null,"multiply_is_zero_y":false,"is_occlusion":false},"texture":null,"ios_texture":{"url":"https://assets.lig.com.tw/ar_asset/n22npdo1a4osym34wyo3vkjvxt18.glb","id":"28487","file_path":"n2/n22npdo1a4osym34wyo3vkjvxt18.glb"},"android_texture":{"url":"https://assets.lig.com.tw/ar_asset/n22npdo1a4osym34wyo3vkjvxt18.glb","id":"28487","file_path":"n2/n22npdo1a4osym34wyo3vkjvxt18.glb"}},"actions":null,"transparency":1.0,"group":1,"zone_id":42,"events":[],"scene_id":4010,"sub_events":null,"is_child":false},{"id":69248,"name":"基本資料-歐亞水獺","location":{"y":-0.60205,"rotate_y":-198.2315,"z":8.12633,"rotate_x":0,"x":0.11363,"rotate_z":0},"zoom":{"z":2.3977,"x":2.3977,"y":2.3977},"configuration":null,"created_at":"2025-10-29T22:49:39.740+08:00","updated_at":"2025-11-24T11:38:49.459+08:00","light_id":null,"ar_object_owner_id":null,"ar_object_owner_type":null,"model":{"type":5,"fields":{"width":1,"height":1,"face_me":true,"is_ignore":false,"visible_distance":20,"is_hidden":false,"is_size_scale_lock":true,"is_allow_pinch":false,"is_double_sided":false,"is_occlusion":false,"bloom_intensity":0,"bloom_radius":0},"texture":{"url":"https://assets.lig.com.tw/ar_asset/y5u2544e7umhd8p42mz842jeigef.png","id":"28488","file_path":"y5/y5u2544e7umhd8p42mz842jeigef.png"},"ios_texture":{},"android_texture":{}},"actions":null,"transparency":0.0,"group":1,"zone_id":42,"events":[{"id":1,"values":{},"actions":[{"id":19,"values":{"group":1,"transparency":0,"delay_time":0,"time":0.10000000149011612}}]}],"scene_id":4010,"sub_events":null,"is_child":false},{"id":69247,"name":"基本資料-亞洲黑熊","location":{"y":-0.5,"rotate_y":0,"rotate_x":0,"x":5.979289999999999,"z":-1.24201,"rotate_z":0},"zoom":{"y":2.4809,"x":2.4809,"z":2.4809},"configuration":null,"created_at":"2025-10-29T22:49:33.593+08:00","updated_at":"2025-11-24T11:42:35.984+08:00","light_id":null,"ar_object_owner_id":null,"ar_object_owner_type":null,"model":{"type":5,"fields":{"width":1,"height":1,"face_me":true,"is_ignore":false,"visible_distance":20,"is_hidden":false,"is_size_scale_lock":true,"is_allow_pinch":false,"is_double_sided":false,"is_occlusion":false,"bloom_intensity":0,"bloom_radius":0},"texture":{"id":"28489","url":"https://assets.lig.com.tw/ar_asset/9fyoxd580dp6tz59r8bnidrkvxgj.png","file_path":"9f/9fyoxd580dp6tz59r8bnidrkvxgj.png"},"ios_texture":{},"android_texture":{}},"actions":null,"transparency":0.0,"group":1,"zone_id":42,"events":[{"id":1,"values":{},"actions":[{"id":19,"values":{"group":1,"transparency":0,"delay_time":0,"time":0.10000000149011612}}]}],"scene_id":4010,"sub_events":null,"is_child":false},{"id":69245,"name":"第4區-亞洲黑熊地標","location":{"y":-2.0,"rotate_y":0.0,"z":-0.97846,"x":5.92752,"rotate_x":0.0,"rotate_z":-0.0},"zoom":{"x":0.1024,"y":0.1024,"z":0.1024},"configuration":null,"created_at":"2025-10-29T03:51:04.315+08:00","updated_at":"2025-11-13T19:33:52.484+08:00","light_id":null,"ar_object_owner_id":null,"ar_object_owner_type":null,"model":{"type":8,"fields":{"visible_distance":20.0,"is_metal":false,"is_hidden":false,"is_allow_pinch":false,"width":1,"height":1,"face_me":true,"is_ignore":false,"is_double_sided":false,"animation_speed":null,"start_frame":null,"end_frame":null,"fps":null,"multiply_number":null,"multiply_radius":null,"multiply_range":null,"multiply_is_zero_y":false,"is_occlusion":false},"texture":null,"ios_texture":{"url":"https://assets.lig.com.tw/ar_asset/n0nu807c9jkmu3gqlr73359tgv2j.glb","id":"28490","file_path":"n0/n0nu807c9jkmu3gqlr73359tgv2j.glb"},"android_texture":{"url":"https://assets.lig.com.tw/ar_asset/n0nu807c9jkmu3gqlr73359tgv2j.glb","id":"28490","file_path":"n0/n0nu807c9jkmu3gqlr73359tgv2j.glb"}},"actions":null,"transparency":1.0,"group":1,"zone_id":42,"events":[{"id":1,"values":{},"actions":[{"id":19,"values":{"group":1,"transparency":1.0,"obj_id":69247,"delay_time":0.0,"time":0.10000000149011612}}]}],"scene_id":4010,"sub_events":{},"is_child":false},{"id":69244,"name":"第4區-歐亞水獺地標","location":{"y":-2.1000000000000005,"rotate_y":180,"z":8.947,"x":0,"rotate_x":0,"rotate_z":0},"zoom":{"y":0.1035,"z":0.1035,"x":0.1035},"configuration":null,"created_at":"2025-10-29T03:51:04.295+08:00","updated_at":"2025-11-24T11:37:42.254+08:00","light_id":null,"ar_object_owner_id":null,"ar_object_owner_type":null,"model":{"type":8,"fields":{"visible_distance":20,"is_metal":false,"is_hidden":false,"is_allow_pinch":false,"width":1,"height":1,"face_me":false,"is_ignore":true,"is_double_sided":false,"animation_speed":null,"start_frame":null,"end_frame":null,"fps":null,"multiply_number":null,"multiply_radius":null,"multiply_range":null,"multiply_is_zero_y":false,"is_occlusion":false},"texture":null,"ios_texture":{"url":"https://assets.lig.com.tw/ar_asset/f5i3sgy75b2876hrlfjonb9pc0s1.glb","id":"28491","file_path":"f5/f5i3sgy75b2876hrlfjonb9pc0s1.glb"},"android_texture":{"url":"https://assets.lig.com.tw/ar_asset/f5i3sgy75b2876hrlfjonb9pc0s1.glb","id":"28491","file_path":"f5/f5i3sgy75b2876hrlfjonb9pc0s1.glb"}},"actions":null,"transparency":1.0,"group":1,"zone_id":42,"events":[{"id":1,"values":{},"actions":[{"id":19,"values":{"group":1,"transparency":1,"obj_id":69248,"delay_time":0,"time":0.10000000149011612}}]}],"scene_id":4010,"sub_events":{},"is_child":false},{"id":69238,"name":"虛擬動物出現位置","location":{"y":-1.99765,"rotate_y":0,"z":0.99088,"x":7.5,"rotate_x":-90,"rotate_z":0},"zoom":{"z":2,"x":2,"y":2},"configuration":null,"created_at":"2025-10-29T03:51:04.119+08:00","updated_at":"2025-12-09T21:53:35.980+08:00","light_id":null,"ar_object_owner_id":null,"ar_object_owner_type":null,"model":{"type":5,"fields":{"width":1,"height":1,"face_me":false,"is_ignore":false,"visible_distance":20,"is_hidden":true,"is_size_scale_lock":true,"is_child":false,"is_allow_pinch":false,"is_double_sided":false,"is_occlusion":false,"bloom_intensity":0,"bloom_radius":0},"texture":{"url":"https://assets.lig.com.tw/ar_asset/0lscss406tlz17jw8t30cz16qgqo.png","id":"28915","file_path":"0l/0lscss406tlz17jw8t30cz16qgqo.png"},"ios_texture":{"content_type":"image/png"},"android_texture":{"content_type":"image/png"}},"actions":null,"transparency":0.0,"group":1,"zone_id":42,"events":[],"scene_id":4010,"sub_events":{},"is_child":false},{"id":69237,"name":"虛擬動物出現位置","location":{"y":-2,"rotate_y":-180,"z":8.5,"rotate_x":-90,"x":-2.5,"rotate_z":0},"zoom":{"z":2,"y":2,"x":2},"configuration":null,"created_at":"2025-10-29T03:51:04.102+08:00","updated_at":"2025-12-09T21:53:33.828+08:00","light_id":null,"ar_object_owner_id":null,"ar_object_owner_type":null,"model":{"type":5,"fields":{"width":1,"height":1,"face_me":false,"is_ignore":false,"visible_distance":20,"is_hidden":true,"is_size_scale_lock":true,"is_child":false,"is_allow_pinch":false,"is_double_sided":false,"is_occlusion":false,"bloom_intensity":0,"bloom_radius":0},"texture":{"url":"https://assets.lig.com.tw/ar_asset/0lscss406tlz17jw8t30cz16qgqo.png","id":"28915","file_path":"0l/0lscss406tlz17jw8t30cz16qgqo.png"},"ios_texture":{"content_type":"image/png"},"android_texture":{"content_type":"image/png"}},"actions":null,"transparency":0.0,"group":1,"zone_id":42,"events":[],"scene_id":4010,"sub_events":{},"is_child":false},{"id":69218,"name":"看AR版-水獺","location":{"y":-0.5,"rotate_y":-198.3181,"z":10.66073,"x":-2.71535,"rotate_x":0.0,"rotate_z":0.0},"zoom":{"x":1.7377,"y":1.7377,"z":1.7377},"configuration":null,"created_at":"2025-10-29T03:51:03.599+08:00","updated_at":"2025-11-24T01:20:28.862+08:00","light_id":null,"ar_object_owner_id":null,"ar_object_owner_type":null,"model":{"type":5,"fields":{"width":1.0,"height":1.0,"face_me":true,"is_ignore":true,"visible_distance":10.0,"is_hidden":false,"is_size_scale_lock":true,"is_allow_pinch":false,"is_double_sided":false,"is_occlusion":false,"bloom_intensity":0.0,"bloom_radius":0.0},"texture":{"url":"https://assets.lig.com.tw/ar_asset/fz38lrcotjv3sqv32y903yhivqpd.png","id":"28492","content_type":"image/png","file_path":"fz/fz38lrcotjv3sqv32y903yhivqpd.png"},"ios_texture":{"content_type":"image/png"},"android_texture":{"content_type":"image/png"}},"actions":null,"transparency":1.0,"group":1,"zone_id":42,"events":[{"id":1,"values":{},"actions":[{"id":7,"values":{"group":1,"obj_id":69208,"delay_time":0.0}},{"id":9,"values":{"group":1,"delay_time":0.0}},{"id":19,"values":{"group":1,"transparency":0.0,"delay_time":0.0,"time":0.10000000149011612}}]}],"scene_id":4010,"sub_events":{},"is_child":false},{"id":69217,"name":"看AR版-黑熊","location":{"y":-1,"rotate_y":0,"z":-0.2500000000000007,"x":7.5,"rotate_x":0,"rotate_z":0},"zoom":{"z":1.6443,"y":1.6443,"x":1.6443},"configuration":null,"created_at":"2025-10-29T03:51:03.575+08:00","updated_at":"2025-11-24T11:39:52.685+08:00","light_id":null,"ar_object_owner_id":null,"ar_object_owner_type":null,"model":{"type":5,"fields":{"width":1,"height":1,"face_me":true,"is_ignore":true,"visible_distance":20,"is_hidden":false,"is_size_scale_lock":true,"is_allow_pinch":false,"is_double_sided":false,"is_occlusion":false,"bloom_intensity":0,"bloom_radius":0},"texture":{"id":"28493","url":"https://assets.lig.com.tw/ar_asset/3m3n2sd9z9rkva2h2ux33wn80c24.png","file_path":"3m/3m3n2sd9z9rkva2h2ux33wn80c24.png"},"ios_texture":{},"android_texture":{}},"actions":null,"transparency":1.0,"group":1,"zone_id":42,"events":[{"id":1,"values":{},"actions":[{"id":7,"values":{"group":1,"delay_time":0,"obj_id":69209}},{"id":19,"values":{"group":1,"transparency":0,"delay_time":0,"time":0.10000000149011612}}]}],"scene_id":4010,"sub_events":{},"is_child":false},{"id":69216,"name":"教育活動_T","location":{"y":-0.5,"rotate_y":0.0,"z":0.3,"x":-3.0,"rotate_x":0.0,"rotate_z":0.0},"zoom":{"x":1.5,"y":1.5,"z":1.5},"configuration":null,"created_at":"2025-10-29T03:51:03.536+08:00","updated_at":"2025-11-06T11:09:08.599+08:00","light_id":null,"ar_object_owner_id":null,"ar_object_owner_type":null,"model":{"type":26,"fields":{"is_child":false,"is_hidden":false,"is_allow_pinch":false,"face_me":false,"is_ignore":false,"visible_distance":20.0,"is_occlusion":false,"is_double_sided":false,"resource_url":"https://api.realitygo.lig.com.tw/api/v1/announcements/activities","type":1},"texture":null,"ios_texture":null,"android_texture":null},"actions":null,"transparency":1.0,"group":1,"zone_id":42,"events":[],"scene_id":4010,"sub_events":{},"is_child":false},{"id":69215,"name":"園區動態_T","location":{"y":-0.5,"rotate_y":0.0,"z":0.3,"x":-5.0,"rotate_x":0.0,"rotate_z":0.0},"zoom":{"x":1.5,"y":1.5,"z":1.5},"configuration":null,"created_at":"2025-10-29T03:51:03.500+08:00","updated_at":"2025-11-06T11:09:29.381+08:00","light_id":null,"ar_object_owner_id":null,"ar_object_owner_type":null,"model":{"type":26,"fields":{"is_child":false,"is_hidden":false,"is_allow_pinch":false,"face_me":false,"is_ignore":false,"visible_distance":20.0,"is_occlusion":false,"is_double_sided":false,"resource_url":"https://api.realitygo.lig.com.tw/api/v1/announcements/zoo-news","type":0},"texture":null,"ios_texture":null,"android_texture":null},"actions":null,"transparency":1.0,"group":1,"zone_id":42,"events":[],"scene_id":4010,"sub_events":{},"is_child":false},{"id":69214,"name":"園區開放時間_T","location":{"y":-0.5,"rotate_y":49.4607,"z":0.9,"x":-9.0,"rotate_x":0.0,"rotate_z":0.0},"zoom":{"x":1.5,"y":1.5,"z":1.5},"configuration":null,"created_at":"2025-10-29T03:51:03.483+08:00","updated_at":"2025-11-06T11:09:53.049+08:00","light_id":null,"ar_object_owner_id":null,"ar_object_owner_type":null,"model":{"type":25,"fields":{"is_child":false,"is_hidden":false,"is_allow_pinch":false,"face_me":false,"is_ignore":false,"visible_distance":20.0,"is_occlusion":false,"is_double_sided":false,"resource_url":"https://api.realitygo.lig.com.tw/api/v1/service-time"},"texture":null,"ios_texture":null,"android_texture":null},"actions":null,"transparency":1.0,"group":1,"zone_id":42,"events":[],"scene_id":4010,"sub_events":{},"is_child":false},{"id":69213,"name":"新聞稿_T","location":{"y":-0.5,"rotate_y":0.0,"z":0.3,"x":-7.0,"rotate_x":0.0,"rotate_z":0.0},"zoom":{"x":1.5,"y":1.5,"z":1.5},"configuration":null,"created_at":"2025-10-29T03:51:03.457+08:00","updated_at":"2025-11-06T11:08:51.283+08:00","light_id":null,"ar_object_owner_id":null,"ar_object_owner_type":null,"model":{"type":26,"fields":{"is_child":false,"is_hidden":false,"is_allow_pinch":false,"face_me":false,"is_ignore":false,"visible_distance":20.0,"is_occlusion":false,"is_double_sided":false,"resource_url":"https://api.realitygo.lig.com.tw/api/v1/announcements/news","type":2},"texture":null,"ios_texture":null,"android_texture":null},"actions":null,"transparency":1.0,"group":1,"zone_id":42,"events":[],"scene_id":4010,"sub_events":{},"is_child":false},{"id":69209,"name":"黑熊_1208_背毛多","location":{"y":-2,"rotate_y":32.9743,"z":0.46357,"x":7.5,"rotate_x":0,"rotate_z":0},"zoom":{"x":0.8487,"z":0.8487,"y":0.8487},"configuration":null,"created_at":"2025-10-29T03:51:03.316+08:00","updated_at":"2025-12-08T23:51:35.896+08:00","light_id":null,"ar_object_owner_id":null,"ar_object_owner_type":null,"model":{"type":8,"fields":{"visible_distance":20,"is_metal":false,"is_hidden":true,"is_allow_pinch":true,"is_allow_rotate":true,"width":1,"height":1,"face_me":false,"is_ignore":true,"is_double_sided":false,"animation_speed":null,"start_frame":null,"end_frame":null,"fps":null,"multiply_number":null,"multiply_radius":null,"multiply_range":null,"multiply_is_zero_y":false,"is_occlusion":false},"texture":null,"ios_texture":{"id":"28914","url":"https://assets.lig.com.tw/ar_asset/467twlh9qcgcb5uc0cz4llng7ebb.glb","file_path":"46/467twlh9qcgcb5uc0cz4llng7ebb.glb"},"android_texture":{"id":"28914","url":"https://assets.lig.com.tw/ar_asset/467twlh9qcgcb5uc0cz4llng7ebb.glb","file_path":"46/467twlh9qcgcb5uc0cz4llng7ebb.glb"}},"actions":null,"transparency":1.0,"group":1,"zone_id":42,"events":[],"scene_id":4010,"sub_events":{},"is_child":false},{"id":69208,"name":"歐亞水獺_1106","location":{"y":-1.0,"rotate_y":0.0,"z":9.59338,"x":-2.15865,"rotate_x":0.0,"rotate_z":-0.0},"zoom":{"x":1.0,"y":1.0,"z":1.0},"configuration":null,"created_at":"2025-10-29T03:51:03.275+08:00","updated_at":"2025-11-13T13:45:33.666+08:00","light_id":null,"ar_object_owner_id":null,"ar_object_owner_type":null,"model":{"type":8,"fields":{"visible_distance":20.0,"is_metal":false,"is_hidden":true,"is_allow_pinch":true,"is_allow_rotate":true,"width":1,"height":1,"face_me":false,"is_ignore":true,"is_double_sided":false,"animation_speed":null,"start_frame":null,"end_frame":null,"fps":null,"multiply_number":null,"multiply_radius":null,"multiply_range":null,"multiply_is_zero_y":false,"is_occlusion":false},"texture":null,"ios_texture":{"url":"https://assets.lig.com.tw/ar_asset/iiip0yjdzfl5zbnvudzq7zf8q81l.glb","id":"28445","file_path":"ii/iiip0yjdzfl5zbnvudzq7zf8q81l.glb"},"android_texture":{"url":"https://assets.lig.com.tw/ar_asset/iiip0yjdzfl5zbnvudzq7zf8q81l.glb","id":"28445","file_path":"ii/iiip0yjdzfl5zbnvudzq7zf8q81l.glb"}},"actions":null,"transparency":1.0,"group":1,"zone_id":42,"events":[],"scene_id":4010,"sub_events":{},"is_child":false},{"id":69202,"name":"智慧燈桿_第四區","location":{"y":-2.0,"rotate_y":0.0,"z":-1.26262,"x":0.65973,"rotate_x":0.0,"rotate_z":0.0},"zoom":{"x":1.9223,"y":1.9223,"z":1.9223},"configuration":null,"created_at":"2025-10-29T03:47:13.396+08:00","updated_at":"2025-11-24T01:19:29.123+08:00","light_id":null,"ar_object_owner_id":null,"ar_object_owner_type":null,"model":{"type":8,"fields":{"visible_distance":20.0,"is_metal":false,"is_hidden":true,"is_allow_pinch":false,"width":1,"height":1,"face_me":false,"is_ignore":true,"is_double_sided":false,"animation_speed":null,"start_frame":null,"end_frame":null,"fps":null,"multiply_number":null,"multiply_radius":null,"multiply_range":null,"multiply_is_zero_y":false,"is_occlusion":false},"texture":null,"ios_texture":{"url":"https://assets.lig.com.tw/ar_asset/swwj41u3f4yutpikb9ya5z04vkb8.glb","id":"28494","file_path":"sw/swwj41u3f4yutpikb9ya5z04vkb8.glb"},"android_texture":{"url":"https://assets.lig.com.tw/ar_asset/swwj41u3f4yutpikb9ya5z04vkb8.glb","id":"28494","file_path":"sw/swwj41u3f4yutpikb9ya5z04vkb8.glb"}},"actions":null,"transparency":1.0,"group":1,"zone_id":42,"events":[{"id":1,"values":{},"actions":[{"id":9,"values":{"group":1,"delay_time":0.0}},{"id":19,"values":{"group":1,"transparency":1.0,"obj_id":69148,"delay_time":0.0,"time":0.10000000149011612}}]}],"scene_id":4010,"sub_events":{},"is_child":false},{"id":69199,"name":"互動地圖_第四區_v2","location":{"y":-1.43482,"rotate_y":90.0,"z":6.2322,"x":-7.91887,"rotate_x":0.0,"rotate_z":0.0},"zoom":{"x":0.4876,"y":0.4876,"z":0.4876},"configuration":null,"created_at":"2025-10-29T03:47:13.355+08:00","updated_at":"2025-11-24T01:19:29.517+08:00","light_id":null,"ar_object_owner_id":null,"ar_object_owner_type":null,"model":{"type":8,"fields":{"visible_distance":20.0,"is_metal":false,"is_hidden":true,"is_allow_pinch":false,"width":1,"height":1,"face_me":false,"is_ignore":true,"is_double_sided":false,"animation_speed":null,"start_frame":null,"end_frame":null,"fps":null,"multiply_number":null,"multiply_radius":null,"multiply_range":null,"multiply_is_zero_y":false,"is_occlusion":false},"texture":null,"ios_texture":{"url":"https://assets.lig.com.tw/ar_asset/pc0l4m3xbb7h9qxchvwiq74e2uqp.glb","id":"28495","file_path":"pc/pc0l4m3xbb7h9qxchvwiq74e2uqp.glb"},"android_texture":{"url":"https://assets.lig.com.tw/ar_asset/pc0l4m3xbb7h9qxchvwiq74e2uqp.glb","id":"28495","file_path":"pc/pc0l4m3xbb7h9qxchvwiq74e2uqp.glb"}},"actions":null,"transparency":1.0,"group":1,"zone_id":42,"events":[],"scene_id":4010,"sub_events":{},"is_child":false},{"id":69194,"name":"1-歡迎頁_組合","location":{"y":-0.02612,"rotate_y":0.0,"z":0.76445,"x":2.45404,"rotate_x":0.0,"rotate_z":0.0},"zoom":{"x":3.6783,"y":3.6783,"z":3.6783},"configuration":null,"created_at":"2025-10-29T03:47:13.280+08:00","updated_at":"2025-11-24T01:19:29.573+08:00","light_id":null,"ar_object_owner_id":null,"ar_object_owner_type":null,"model":{"type":5,"fields":{"width":1.0,"height":1.0,"face_me":false,"is_ignore":true,"visible_distance":20.0,"is_hidden":false,"is_size_scale_lock":true,"is_child":false,"is_allow_pinch":false,"is_double_sided":true,"is_occlusion":false,"bloom_intensity":0.0,"bloom_radius":0.0},"texture":{"url":"https://assets.lig.com.tw/ar_asset/1e5dk8php3uhpcn85ackkhre9isb.png","id":"28424","content_type":"image/png","file_path":"1e/1e5dk8php3uhpcn85ackkhre9isb.png"},"ios_texture":{"content_type":"image/png"},"android_texture":{"content_type":"image/png"}},"actions":null,"transparency":0.0,"group":1,"zone_id":42,"events":[{"id":1,"values":{},"actions":[{"id":19,"values":{"group":1,"transparency":0.0,"delay_time":0.0,"time":0.0}},{"id":19,"values":{"group":2,"transparency":1.0,"obj_id":69174,"delay_time":0.0,"time":0.20000000298023224}}]}],"scene_id":4010,"sub_events":{},"is_child":false},{"id":69190,"name":"水獺導覽員_v23","location":{"y":-0.58725,"rotate_y":-0.0,"z":0.6,"x":0.0,"rotate_x":0.0,"rotate_z":-0.0},"zoom":{"x":1.0,"y":1.0,"z":1.0},"configuration":null,"created_at":"2025-10-29T03:47:13.215+08:00","updated_at":"2025-11-13T13:45:34.095+08:00","light_id":null,"ar_object_owner_id":null,"ar_object_owner_type":null,"model":{"type":8,"fields":{"visible_distance":20.0,"is_metal":false,"is_hidden":false,"is_allow_pinch":false,"width":1,"height":1,"face_me":false,"is_ignore":false,"is_double_sided":false,"animation_speed":null,"start_frame":null,"end_frame":null,"fps":null,"multiply_number":null,"multiply_radius":null,"multiply_range":null,"multiply_is_zero_y":false,"is_occlusion":false},"texture":null,"ios_texture":{"url":"https://assets.lig.com.tw/ar_asset/h64x8yzcslymvr7006ox80jd0osa.glb","id":"28423","file_path":"h6/h64x8yzcslymvr7006ox80jd0osa.glb"},"android_texture":{"url":"https://assets.lig.com.tw/ar_asset/h64x8yzcslymvr7006ox80jd0osa.glb","id":"28423","file_path":"h6/h64x8yzcslymvr7006ox80jd0osa.glb"}},"actions":null,"transparency":1.0,"group":1,"zone_id":42,"events":[],"scene_id":4010,"sub_events":{},"is_child":false},{"id":69189,"name":"觸發-互動地圖-白鼻心","location":{"y":0.21846,"rotate_y":-96.7014,"z":7.75895,"x":-7.86433,"rotate_x":0.0,"rotate_z":0.0},"zoom":{"x":0.2342,"y":0.16,"z":0.0675},"configuration":null,"created_at":"2025-10-29T03:47:13.201+08:00","updated_at":"2026-01-15T18:02:46.875+08:00","light_id":null,"ar_object_owner_id":null,"ar_object_owner_type":null,"model":{"type":8,"fields":{"visible_distance":20.0,"is_metal":false,"is_child":false,"is_hidden":false,"is_allow_pinch":false,"width":1.0,"height":1.0,"face_me":false,"is_ignore":false,"is_double_sided":false,"animation_speed":null,"start_frame":null,"end_frame":null,"fps":null,"multiply_number":0,"multiply_radius":0.0,"multiply_range":0.0,"multiply_is_zero_y":false,"is_occlusion":false,"thumbnail":null},"texture":null,"ios_texture":{"url":"https://assets.lig.com.tw/ar_asset/7k0l223dlvkjqix756i1k9ser522.glb","id":"28391","file_path":"7k/7k0l223dlvkjqix756i1k9ser522.glb"},"android_texture":{"url":"https://assets.lig.com.tw/ar_asset/7k0l223dlvkjqix756i1k9ser522.glb","id":"28391","file_path":"7k/7k0l223dlvkjqix756i1k9ser522.glb"}},"actions":null,"transparency":1.0,"group":1,"zone_id":42,"events":[{"id":1,"values":{},"actions":[{"id":8,"values":{"auth":false,"delay_time":0.0,"url":"https://aiar.zoo.gov.taipei/animals/11?inwv=1"}},{"id":19,"values":{"group":1,"transparency":0.0,"delay_time":0.0,"time":0.10000000149011612}},{"id":19,"values":{"group":2,"transparency":1.0,"delay_time":0.0,"time":0.10000000149011612}}]}],"scene_id":4010,"sub_events":{},"is_child":false},{"id":69188,"name":"觸發-互動地圖-石虎","location":{"y":0.23316,"rotate_y":80.875,"z":5.8449,"x":-8.28641,"rotate_x":0.0,"rotate_z":0.0},"zoom":{"x":0.2027,"y":0.1431,"z":0.0675},"configuration":null,"created_at":"2025-10-29T03:47:13.183+08:00","updated_at":"2026-01-15T18:02:46.883+08:00","light_id":null,"ar_object_owner_id":null,"ar_object_owner_type":null,"model":{"type":8,"fields":{"visible_distance":20.0,"is_metal":false,"is_child":false,"is_hidden":false,"is_allow_pinch":false,"width":1.0,"height":1.0,"face_me":false,"is_ignore":false,"is_double_sided":false,"animation_speed":null,"start_frame":null,"end_frame":null,"fps":null,"multiply_number":0,"multiply_radius":0.0,"multiply_range":0.0,"multiply_is_zero_y":false,"is_occlusion":false,"thumbnail":null},"texture":null,"ios_texture":{"url":"https://assets.lig.com.tw/ar_asset/7k0l223dlvkjqix756i1k9ser522.glb","id":"28391","file_path":"7k/7k0l223dlvkjqix756i1k9ser522.glb"},"android_texture":{"url":"https://assets.lig.com.tw/ar_asset/7k0l223dlvkjqix756i1k9ser522.glb","id":"28391","file_path":"7k/7k0l223dlvkjqix756i1k9ser522.glb"}},"actions":null,"transparency":1.0,"group":1,"zone_id":42,"events":[{"id":1,"values":{},"actions":[{"id":8,"values":{"auth":false,"delay_time":0.0,"url":"https://aiar.zoo.gov.taipei/animals/6?inwv=1"}},{"id":19,"values":{"group":1,"transparency":0.0,"delay_time":0.0,"time":0.10000000149011612}},{"id":19,"values":{"group":2,"transparency":1.0,"delay_time":0.0,"time":0.10000000149011612}}]}],"scene_id":4010,"sub_events":{},"is_child":false},{"id":69187,"name":"觸發-互動地圖-亞洲黑熊","location":{"y":0.63291,"rotate_y":-96.6396,"z":5.82766,"x":-8.93912,"rotate_x":0.0,"rotate_z":0.0},"zoom":{"x":0.3008,"y":0.166,"z":0.0675},"configuration":null,"created_at":"2025-10-29T03:47:13.166+08:00","updated_at":"2026-01-15T18:02:46.890+08:00","light_id":null,"ar_object_owner_id":null,"ar_object_owner_type":null,"model":{"type":8,"fields":{"visible_distance":20.0,"is_metal":false,"is_child":false,"is_hidden":false,"is_allow_pinch":false,"width":1.0,"height":1.0,"face_me":false,"is_ignore":false,"is_double_sided":false,"animation_speed":null,"start_frame":null,"end_frame":null,"fps":null,"multiply_number":0,"multiply_radius":0.0,"multiply_range":0.0,"multiply_is_zero_y":false,"is_occlusion":false,"thumbnail":null},"texture":null,"ios_texture":{"url":"https://assets.lig.com.tw/ar_asset/7k0l223dlvkjqix756i1k9ser522.glb","id":"28391","file_path":"7k/7k0l223dlvkjqix756i1k9ser522.glb"},"android_texture":{"url":"https://assets.lig.com.tw/ar_asset/7k0l223dlvkjqix756i1k9ser522.glb","id":"28391","file_path":"7k/7k0l223dlvkjqix756i1k9ser522.glb"}},"actions":null,"transparency":1.0,"group":1,"zone_id":42,"events":[{"id":1,"values":{},"actions":[{"id":8,"values":{"auth":false,"delay_time":0.0,"url":"https://aiar.zoo.gov.taipei/animals/7?inwv=1"}},{"id":19,"values":{"group":1,"transparency":0.0,"delay_time":0.0,"time":0.10000000149011612}},{"id":19,"values":{"group":2,"transparency":1.0,"delay_time":0.0,"time":0.10000000149011612}}]}],"scene_id":4010,"sub_events":{},"is_child":false},{"id":69186,"name":"觸發-互動地圖-食蛇龜","location":{"y":0.12204,"rotate_y":-95.3294,"z":4.92923,"x":-8.02226,"rotate_x":0.0,"rotate_z":0.0},"zoom":{"x":0.2801,"y":0.1409,"z":0.0675},"configuration":null,"created_at":"2025-10-29T03:47:13.148+08:00","updated_at":"2026-01-15T18:02:46.896+08:00","light_id":null,"ar_object_owner_id":null,"ar_object_owner_type":null,"model":{"type":8,"fields":{"visible_distance":20.0,"is_metal":false,"is_child":false,"is_hidden":false,"is_allow_pinch":false,"width":1.0,"height":1.0,"face_me":false,"is_ignore":false,"is_double_sided":false,"animation_speed":null,"start_frame":null,"end_frame":null,"fps":null,"multiply_number":0,"multiply_radius":0.0,"multiply_range":0.0,"multiply_is_zero_y":false,"is_occlusion":false,"thumbnail":null},"texture":null,"ios_texture":{"url":"https://assets.lig.com.tw/ar_asset/7k0l223dlvkjqix756i1k9ser522.glb","id":"28391","file_path":"7k/7k0l223dlvkjqix756i1k9ser522.glb"},"android_texture":{"url":"https://assets.lig.com.tw/ar_asset/7k0l223dlvkjqix756i1k9ser522.glb","id":"28391","file_path":"7k/7k0l223dlvkjqix756i1k9ser522.glb"}},"actions":null,"transparency":1.0,"group":1,"zone_id":42,"events":[{"id":1,"values":{},"actions":[{"id":8,"values":{"auth":false,"delay_time":0.0,"url":"https://aiar.zoo.gov.taipei/animals/16?inwv=1"}},{"id":19,"values":{"group":1,"transparency":0.0,"delay_time":0.0,"time":0.10000000149011612}},{"id":19,"values":{"group":2,"transparency":1.0,"delay_time":0.0,"time":0.10000000149011612}}]}],"scene_id":4010,"sub_events":{},"is_child":false},{"id":69185,"name":"觸發-互動地圖-雲豹","location":{"y":0.40261,"rotate_y":-86.5627,"z":5.28541,"x":-8.39371,"rotate_x":0.0,"rotate_z":0.0},"zoom":{"x":0.2227,"y":0.1397,"z":0.0675},"configuration":null,"created_at":"2025-10-29T03:47:13.131+08:00","updated_at":"2026-01-15T18:02:46.899+08:00","light_id":null,"ar_object_owner_id":null,"ar_object_owner_type":null,"model":{"type":8,"fields":{"visible_distance":20.0,"is_metal":false,"is_child":false,"is_hidden":false,"is_allow_pinch":false,"width":1.0,"height":1.0,"face_me":false,"is_ignore":false,"is_double_sided":false,"animation_speed":null,"start_frame":null,"end_frame":null,"fps":null,"multiply_number":0,"multiply_radius":0.0,"multiply_range":0.0,"multiply_is_zero_y":false,"is_occlusion":false,"thumbnail":null},"texture":null,"ios_texture":{"url":"https://assets.lig.com.tw/ar_asset/7k0l223dlvkjqix756i1k9ser522.glb","id":"28391","file_path":"7k/7k0l223dlvkjqix756i1k9ser522.glb"},"android_texture":{"url":"https://assets.lig.com.tw/ar_asset/7k0l223dlvkjqix756i1k9ser522.glb","id":"28391","file_path":"7k/7k0l223dlvkjqix756i1k9ser522.glb"}},"actions":null,"transparency":1.0,"group":1,"zone_id":42,"events":[{"id":1,"values":{},"actions":[{"id":8,"values":{"auth":false,"delay_time":0.0,"url":"https://aiar.zoo.gov.taipei/animals/5?inwv=1"}},{"id":19,"values":{"group":1,"transparency":0.0,"delay_time":0.0,"time":0.10000000149011612}},{"id":19,"values":{"group":2,"transparency":1.0,"delay_time":0.0,"time":0.10000000149011612}}]}],"scene_id":4010,"sub_events":{},"is_child":false},{"id":69184,"name":"觸發-互動地圖-中華穿山甲","location":{"y":-0.10904,"rotate_y":-91.4128,"z":7.94788,"x":-7.32879,"rotate_x":0.0,"rotate_z":0.0},"zoom":{"x":0.2632,"y":0.1573,"z":0.0675},"configuration":null,"created_at":"2025-10-29T03:47:13.113+08:00","updated_at":"2026-01-15T18:02:46.961+08:00","light_id":null,"ar_object_owner_id":null,"ar_object_owner_type":null,"model":{"type":8,"fields":{"visible_distance":20.0,"is_metal":false,"is_child":false,"is_hidden":false,"is_allow_pinch":false,"width":1.0,"height":1.0,"face_me":false,"is_ignore":false,"is_double_sided":false,"animation_speed":null,"start_frame":null,"end_frame":null,"fps":null,"multiply_number":0,"multiply_radius":0.0,"multiply_range":0.0,"multiply_is_zero_y":false,"is_occlusion":false,"thumbnail":null},"texture":null,"ios_texture":{"url":"https://assets.lig.com.tw/ar_asset/7k0l223dlvkjqix756i1k9ser522.glb","id":"28391","file_path":"7k/7k0l223dlvkjqix756i1k9ser522.glb"},"android_texture":{"url":"https://assets.lig.com.tw/ar_asset/7k0l223dlvkjqix756i1k9ser522.glb","id":"28391","file_path":"7k/7k0l223dlvkjqix756i1k9ser522.glb"}},"actions":null,"transparency":1.0,"group":1,"zone_id":42,"events":[{"id":1,"values":{},"actions":[{"id":8,"values":{"auth":false,"delay_time":0.0,"url":"https://aiar.zoo.gov.taipei/animals/10?inwv=1"}},{"id":19,"values":{"group":1,"transparency":0.0,"delay_time":0.0,"time":0.10000000149011612}},{"id":19,"values":{"group":2,"transparency":1.0,"delay_time":0.0,"time":0.10000000149011612}}]}],"scene_id":4010,"sub_events":{},"is_child":false},{"id":69183,"name":"觸發-互動地圖-台灣野山羊","location":{"y":0.54188,"rotate_y":-102.2158,"z":6.83542,"x":-8.8302,"rotate_x":0.0,"rotate_z":0.0},"zoom":{"x":0.3263,"y":0.1474,"z":0.0675},"configuration":null,"created_at":"2025-10-29T03:47:13.095+08:00","updated_at":"2026-01-15T18:02:46.965+08:00","light_id":null,"ar_object_owner_id":null,"ar_object_owner_type":null,"model":{"type":8,"fields":{"visible_distance":20.0,"is_metal":false,"is_child":false,"is_hidden":false,"is_allow_pinch":false,"width":1.0,"height":1.0,"face_me":false,"is_ignore":false,"is_double_sided":false,"animation_speed":null,"start_frame":null,"end_frame":null,"fps":null,"multiply_number":0,"multiply_radius":0.0,"multiply_range":0.0,"multiply_is_zero_y":false,"is_occlusion":false,"thumbnail":null},"texture":null,"ios_texture":{"url":"https://assets.lig.com.tw/ar_asset/7k0l223dlvkjqix756i1k9ser522.glb","id":"28391","file_path":"7k/7k0l223dlvkjqix756i1k9ser522.glb"},"android_texture":{"url":"https://assets.lig.com.tw/ar_asset/7k0l223dlvkjqix756i1k9ser522.glb","id":"28391","file_path":"7k/7k0l223dlvkjqix756i1k9ser522.glb"}},"actions":null,"transparency":1.0,"group":1,"zone_id":42,"events":[{"id":1,"values":{},"actions":[{"id":8,"values":{"auth":false,"delay_time":0.0,"url":"https://aiar.zoo.gov.taipei/animals/9?inwv=1"}},{"id":19,"values":{"group":1,"transparency":0.0,"delay_time":0.0,"time":0.10000000149011612}},{"id":19,"values":{"group":2,"transparency":1.0,"delay_time":0.0,"time":0.10000000149011612}}]}],"scene_id":4010,"sub_events":{},"is_child":false},{"id":69182,"name":"觸發-互動地圖-台灣獼猴","location":{"y":-0.58326,"rotate_y":-96.8899,"z":6.80879,"x":-7.76091,"rotate_x":0.0,"rotate_z":0.0},"zoom":{"x":0.2934,"y":0.1411,"z":0.0675},"configuration":null,"created_at":"2025-10-29T03:47:13.077+08:00","updated_at":"2026-01-15T18:02:46.968+08:00","light_id":null,"ar_object_owner_id":null,"ar_object_owner_type":null,"model":{"type":8,"fields":{"visible_distance":20.0,"is_metal":false,"is_child":false,"is_hidden":false,"is_allow_pinch":false,"width":1.0,"height":1.0,"face_me":false,"is_ignore":false,"is_double_sided":false,"animation_speed":null,"start_frame":null,"end_frame":null,"fps":null,"multiply_number":0,"multiply_radius":0.0,"multiply_range":0.0,"multiply_is_zero_y":false,"is_occlusion":false,"thumbnail":null},"texture":null,"ios_texture":{"url":"https://assets.lig.com.tw/ar_asset/7k0l223dlvkjqix756i1k9ser522.glb","id":"28391","file_path":"7k/7k0l223dlvkjqix756i1k9ser522.glb"},"android_texture":{"url":"https://assets.lig.com.tw/ar_asset/7k0l223dlvkjqix756i1k9ser522.glb","id":"28391","file_path":"7k/7k0l223dlvkjqix756i1k9ser522.glb"}},"actions":null,"transparency":1.0,"group":1,"zone_id":42,"events":[{"id":1,"values":{},"actions":[{"id":8,"values":{"auth":false,"delay_time":0.0,"url":"https://aiar.zoo.gov.taipei/animals/13?inwv=1"}},{"id":19,"values":{"group":1,"transparency":0.0,"delay_time":0.0,"time":0.10000000149011612}},{"id":19,"values":{"group":2,"transparency":1.0,"delay_time":0.0,"time":0.10000000149011612}}]}],"scene_id":4010,"sub_events":{},"is_child":false},{"id":69181,"name":"觸發-互動地圖-領角鴞","location":{"y":0.78828,"rotate_y":-96.7681,"z":5.06585,"x":-8.31343,"rotate_x":0.0,"rotate_z":0.0},"zoom":{"x":0.2632,"y":0.1474,"z":0.0675},"configuration":null,"created_at":"2025-10-29T03:47:13.059+08:00","updated_at":"2026-01-15T18:02:46.972+08:00","light_id":null,"ar_object_owner_id":null,"ar_object_owner_type":null,"model":{"type":8,"fields":{"visible_distance":20.0,"is_metal":false,"is_child":false,"is_hidden":false,"is_allow_pinch":false,"width":1,"height":1,"face_me":false,"is_ignore":false,"is_double_sided":false,"animation_speed":null,"start_frame":null,"end_frame":null,"fps":null,"multiply_number":0,"multiply_radius":0,"multiply_range":0,"multiply_is_zero_y":false,"is_occlusion":false,"thumbnail":null},"texture":null,"ios_texture":{"url":"https://assets.lig.com.tw/ar_asset/7k0l223dlvkjqix756i1k9ser522.glb","id":"28391","file_path":"7k/7k0l223dlvkjqix756i1k9ser522.glb"},"android_texture":{"url":"https://assets.lig.com.tw/ar_asset/7k0l223dlvkjqix756i1k9ser522.glb","id":"28391","file_path":"7k/7k0l223dlvkjqix756i1k9ser522.glb"}},"actions":null,"transparency":1.0,"group":1,"zone_id":42,"events":[{"id":1,"values":{},"actions":[{"id":8,"values":{"auth":false,"group":1,"delay_time":0.0,"url":"https://aiar.zoo.gov.taipei/animals/0?inwv=1"}},{"id":19,"values":{"group":1,"transparency":0.0,"delay_time":0.0,"time":0.10000000149011612}},{"id":19,"values":{"group":2,"transparency":1.0,"delay_time":0.0,"time":0.10000000149011612}}]}],"scene_id":4010,"sub_events":{},"is_child":false},{"id":69180,"name":"觸發-互動地圖-歐亞水獺","location":{"y":-0.08976,"rotate_y":80.875,"z":6.24192,"x":-8.2924,"rotate_x":0.0,"rotate_z":0.0},"zoom":{"x":0.2909,"y":0.1746,"z":0.0675},"configuration":null,"created_at":"2025-10-29T03:47:13.042+08:00","updated_at":"2026-01-15T18:02:46.974+08:00","light_id":null,"ar_object_owner_id":null,"ar_object_owner_type":null,"model":{"type":8,"fields":{"visible_distance":20.0,"is_metal":false,"is_child":false,"is_hidden":false,"is_allow_pinch":false,"width":1.0,"height":1.0,"face_me":false,"is_ignore":false,"is_double_sided":false,"animation_speed":null,"start_frame":null,"end_frame":null,"fps":null,"multiply_number":0,"multiply_radius":0.0,"multiply_range":0.0,"multiply_is_zero_y":false,"is_occlusion":false,"thumbnail":null},"texture":null,"ios_texture":{"url":"https://assets.lig.com.tw/ar_asset/7k0l223dlvkjqix756i1k9ser522.glb","id":"28391","file_path":"7k/7k0l223dlvkjqix756i1k9ser522.glb"},"android_texture":{"url":"https://assets.lig.com.tw/ar_asset/7k0l223dlvkjqix756i1k9ser522.glb","id":"28391","file_path":"7k/7k0l223dlvkjqix756i1k9ser522.glb"}},"actions":null,"transparency":1.0,"group":1,"zone_id":42,"events":[{"id":1,"values":{},"actions":[{"id":8,"values":{"auth":false,"delay_time":0.0,"url":"https://aiar.zoo.gov.taipei/animals/8?inwv=1"}},{"id":19,"values":{"group":1,"transparency":0.0,"delay_time":0.0,"time":0.10000000149011612}},{"id":19,"values":{"group":2,"transparency":1.0,"delay_time":0.0,"time":0.10000000149011612}}]}],"scene_id":4010,"sub_events":{},"is_child":false},{"id":69179,"name":"觸發-互動地圖-藍腹鷴","location":{"y":-0.1408,"rotate_y":-98.2573,"z":5.12405,"x":-7.79205,"rotate_x":0.0,"rotate_z":0.0},"zoom":{"x":0.2632,"y":0.1474,"z":0.0675},"configuration":null,"created_at":"2025-10-29T03:47:13.027+08:00","updated_at":"2026-01-15T18:02:46.977+08:00","light_id":null,"ar_object_owner_id":null,"ar_object_owner_type":null,"model":{"type":8,"fields":{"visible_distance":20.0,"is_metal":false,"is_child":false,"is_hidden":false,"is_allow_pinch":false,"width":1.0,"height":1.0,"face_me":false,"is_ignore":false,"is_double_sided":false,"animation_speed":null,"start_frame":null,"end_frame":null,"fps":null,"multiply_number":0,"multiply_radius":0.0,"multiply_range":0.0,"multiply_is_zero_y":false,"is_occlusion":false,"thumbnail":null},"texture":null,"ios_texture":{"url":"https://assets.lig.com.tw/ar_asset/7k0l223dlvkjqix756i1k9ser522.glb","id":"28391","file_path":"7k/7k0l223dlvkjqix756i1k9ser522.glb"},"android_texture":{"url":"https://assets.lig.com.tw/ar_asset/7k0l223dlvkjqix756i1k9ser522.glb","id":"28391","file_path":"7k/7k0l223dlvkjqix756i1k9ser522.glb"}},"actions":null,"transparency":1.0,"group":1,"zone_id":42,"events":[{"id":1,"values":{},"actions":[{"id":8,"values":{"auth":false,"delay_time":0.0,"url":"https://aiar.zoo.gov.taipei/animals/2?inwv=1"}},{"id":19,"values":{"group":1,"transparency":0.0,"delay_time":0.0,"time":0.10000000149011612}},{"id":19,"values":{"group":2,"transparency":1.0,"delay_time":0.0,"time":0.10000000149011612}}]}],"scene_id":4010,"sub_events":{},"is_child":false},{"id":69178,"name":"觸發-互動地圖-野豬","location":{"y":-0.38448,"rotate_y":-99.8118,"z":4.82377,"x":-7.39598,"rotate_x":0.0,"rotate_z":0.0},"zoom":{"x":0.3375,"y":0.1512,"z":0.0675},"configuration":null,"created_at":"2025-10-29T03:47:13.008+08:00","updated_at":"2026-01-15T18:02:46.980+08:00","light_id":null,"ar_object_owner_id":null,"ar_object_owner_type":null,"model":{"type":8,"fields":{"visible_distance":20.0,"is_metal":false,"is_child":false,"is_hidden":false,"is_allow_pinch":false,"width":1,"height":1,"face_me":false,"is_ignore":false,"is_double_sided":false,"animation_speed":null,"start_frame":null,"end_frame":null,"fps":null,"multiply_number":0,"multiply_radius":0,"multiply_range":0,"multiply_is_zero_y":false,"is_occlusion":false,"thumbnail":null},"texture":null,"ios_texture":{"url":"https://assets.lig.com.tw/ar_asset/7k0l223dlvkjqix756i1k9ser522.glb","id":"28391","file_path":"7k/7k0l223dlvkjqix756i1k9ser522.glb"},"android_texture":{"url":"https://assets.lig.com.tw/ar_asset/7k0l223dlvkjqix756i1k9ser522.glb","id":"28391","file_path":"7k/7k0l223dlvkjqix756i1k9ser522.glb"}},"actions":null,"transparency":1.0,"group":1,"zone_id":42,"events":[{"id":1,"values":{},"actions":[{"id":8,"values":{"auth":false,"delay_time":0.0,"url":"https://aiar.zoo.gov.taipei/animals/4?inwv=1"}},{"id":19,"values":{"group":1,"transparency":0.0,"delay_time":0.0,"time":0.10000000149011612}},{"id":19,"values":{"group":2,"transparency":1.0,"delay_time":0.0,"time":0.10000000149011612}}]}],"scene_id":4010,"sub_events":{},"is_child":false},{"id":69177,"name":"觸發-互動地圖-梅花鹿","location":{"y":-0.65035,"rotate_y":-97.6377,"z":5.33344,"x":-7.23537,"rotate_x":0.0,"rotate_z":0.0},"zoom":{"x":0.2632,"y":0.1388,"z":0.0675},"configuration":null,"created_at":"2025-10-29T03:47:12.990+08:00","updated_at":"2026-01-15T18:02:46.983+08:00","light_id":null,"ar_object_owner_id":null,"ar_object_owner_type":null,"model":{"type":8,"fields":{"visible_distance":20.0,"is_metal":false,"is_child":false,"is_hidden":false,"is_allow_pinch":false,"width":1.0,"height":1.0,"face_me":false,"is_ignore":false,"is_double_sided":false,"animation_speed":null,"start_frame":null,"end_frame":null,"fps":null,"multiply_number":0,"multiply_radius":0.0,"multiply_range":0.0,"multiply_is_zero_y":false,"is_occlusion":false,"thumbnail":null},"texture":null,"ios_texture":{"url":"https://assets.lig.com.tw/ar_asset/7k0l223dlvkjqix756i1k9ser522.glb","id":"28391","file_path":"7k/7k0l223dlvkjqix756i1k9ser522.glb"},"android_texture":{"url":"https://assets.lig.com.tw/ar_asset/7k0l223dlvkjqix756i1k9ser522.glb","id":"28391","file_path":"7k/7k0l223dlvkjqix756i1k9ser522.glb"}},"actions":null,"transparency":1.0,"group":1,"zone_id":42,"events":[{"id":1,"values":{},"actions":[{"id":8,"values":{"auth":false,"delay_time":0.0,"url":"https://aiar.zoo.gov.taipei/animals/3?inwv=1"}},{"id":19,"values":{"group":1,"transparency":0.0,"delay_time":0.0,"time":0.10000000149011612}},{"id":19,"values":{"group":2,"transparency":1.0,"delay_time":0.0,"time":0.10000000149011612}}]}],"scene_id":4010,"sub_events":{},"is_child":false},{"id":69174,"name":"導覽員-水獺頭上的i","location":{"y":-0.33614,"rotate_y":-0.0,"z":0.6,"x":2.17568,"rotate_x":0.0,"rotate_z":0.0},"zoom":{"x":1.2795,"y":1.2795,"z":1.2795},"configuration":null,"created_at":"2025-10-29T03:47:12.939+08:00","updated_at":"2025-11-13T19:33:54.834+08:00","light_id":null,"ar_object_owner_id":null,"ar_object_owner_type":null,"model":{"type":5,"fields":{"width":1.0,"height":1.0,"face_me":false,"is_ignore":false,"visible_distance":20.0,"is_hidden":false,"is_size_scale_lock":true,"is_allow_pinch":false,"is_double_sided":false,"is_occlusion":false,"bloom_intensity":0.0,"bloom_radius":0.0},"texture":{"url":"https://assets.lig.com.tw/ar_asset/vxdet54dyok19tep37am3bctl2rk.png","id":"28421","content_type":"image/png","file_path":"vx/vxdet54dyok19tep37am3bctl2rk.png"},"ios_texture":{"content_type":"image/png"},"android_texture":{"content_type":"image/png"}},"actions":null,"transparency":1.0,"group":1,"zone_id":42,"events":[{"id":1,"values":{},"actions":[{"id":19,"values":{"group":1,"transparency":0.0,"delay_time":0.0,"time":0.20000000298023224}},{"id":19,"values":{"group":2,"transparency":1.0,"obj_id":69194,"delay_time":0.0,"time":0.20000000298023224}}]}],"scene_id":4010,"sub_events":{},"is_child":false},{"id":69173,"name":"互動地圖-小提示_step1","location":{"y":-1.12868,"rotate_y":90.0,"z":2.53763,"x":-6.12549,"rotate_x":0.0,"rotate_z":0.0},"zoom":{"x":2.0109,"y":2.0109,"z":2.0109},"configuration":null,"created_at":"2025-10-29T03:47:12.919+08:00","updated_at":"2025-11-24T01:19:30.564+08:00","light_id":null,"ar_object_owner_id":null,"ar_object_owner_type":null,"model":{"type":5,"fields":{"width":1.0,"height":1.0,"face_me":false,"is_ignore":false,"visible_distance":20.0,"is_hidden":false,"is_size_scale_lock":true,"is_allow_pinch":false,"is_double_sided":true,"is_occlusion":false,"bloom_intensity":0.0,"bloom_radius":0.0},"texture":{"url":"https://assets.lig.com.tw/ar_asset/o423uowdl0jz6aro0is9dclqh9mi.png","id":"28420","content_type":"image/png","file_path":"o4/o423uowdl0jz6aro0is9dclqh9mi.png"},"ios_texture":{"content_type":"image/png"},"android_texture":{"content_type":"image/png"}},"actions":null,"transparency":0.0,"group":1,"zone_id":42,"events":[{"id":1,"values":{},"actions":[{"id":19,"values":{"group":1,"transparency":0.0,"delay_time":0.0,"time":0.10000000149011612}},{"id":19,"values":{"group":1,"transparency":1.0,"obj_id":69172,"delay_time":0.0,"time":0.10000000149011612}}]}],"scene_id":4010,"sub_events":{},"is_child":false},{"id":69172,"name":"互動地圖-小提示_step2","location":{"y":-1.12868,"rotate_y":90.0,"z":2.53763,"x":-6.12549,"rotate_x":0.0,"rotate_z":0.0},"zoom":{"x":2.0109,"y":2.0109,"z":2.0109},"configuration":null,"created_at":"2025-10-29T03:47:12.823+08:00","updated_at":"2025-11-24T01:19:30.503+08:00","light_id":null,"ar_object_owner_id":null,"ar_object_owner_type":null,"model":{"type":5,"fields":{"width":1.0,"height":1.0,"face_me":false,"is_ignore":false,"visible_distance":20.0,"is_hidden":false,"is_size_scale_lock":true,"is_allow_pinch":false,"is_double_sided":false,"is_occlusion":false,"bloom_intensity":0.0,"bloom_radius":0.0},"texture":{"url":"https://assets.lig.com.tw/ar_asset/2adpzz5v52lbvg5itzo87pemsxfc.png","id":"28419","content_type":"image/png","file_path":"2a/2adpzz5v52lbvg5itzo87pemsxfc.png"},"ios_texture":{"content_type":"image/png"},"android_texture":{"content_type":"image/png"}},"actions":null,"transparency":0.0,"group":1,"zone_id":42,"events":[],"scene_id":4010,"sub_events":{},"is_child":false},{"id":69171,"name":"強制教學面板_中_第一區","location":{"y":0.21728,"rotate_y":0.0,"z":0.77416,"x":1.68833,"rotate_x":0.0,"rotate_z":0.0},"zoom":{"x":3.8189,"y":3.8189,"z":3.8189},"configuration":null,"created_at":"2025-10-29T03:47:12.787+08:00","updated_at":"2025-11-24T01:19:31.019+08:00","light_id":null,"ar_object_owner_id":null,"ar_object_owner_type":null,"model":{"type":5,"fields":{"width":1.0,"height":1.0,"face_me":false,"is_ignore":false,"visible_distance":20.0,"is_hidden":false,"is_size_scale_lock":true,"is_allow_pinch":false,"is_double_sided":true,"is_occlusion":false,"bloom_intensity":0.0,"bloom_radius":0.0},"texture":{"url":"https://assets.lig.com.tw/ar_asset/xwwqs10mzaz5cgini5d6nbollx23.png","id":"28418","content_type":"image/png","file_path":"xw/xwwqs10mzaz5cgini5d6nbollx23.png"},"ios_texture":{"content_type":"image/png"},"android_texture":{"content_type":"image/png"}},"actions":null,"transparency":0.0,"group":1,"zone_id":42,"events":[{"id":1,"values":{},"actions":[{"id":19,"values":{"group":1,"transparency":0.0,"delay_time":0.0,"time":0.10000000149011612}},{"id":19,"values":{"group":1,"transparency":1.0,"obj_id":69150,"delay_time":0.0,"time":0.10000000149011612}}]}],"scene_id":4010,"sub_events":{},"is_child":false},{"id":69170,"name":"左轉_互動地圖_v2","location":{"y":-1.33769,"rotate_y":0,"rotate_x":0,"z":0.62432,"x":-2.50511,"rotate_z":0},"zoom":{"z":0.0343,"y":0.0343,"x":0.0343},"configuration":null,"created_at":"2025-10-29T03:47:12.771+08:00","updated_at":"2025-12-08T03:57:32.458+08:00","light_id":null,"ar_object_owner_id":null,"ar_object_owner_type":null,"model":{"type":8,"fields":{"visible_distance":20,"is_metal":false,"is_hidden":true,"is_allow_pinch":false,"width":1,"height":1,"face_me":false,"is_ignore":true,"is_double_sided":false,"animation_speed":null,"start_frame":null,"end_frame":null,"fps":null,"multiply_number":null,"multiply_radius":null,"multiply_range":null,"multiply_is_zero_y":false,"is_occlusion":false},"texture":null,"ios_texture":{"id":"28414","url":"https://assets.lig.com.tw/ar_asset/3kew42vdedd433vbl575xysp9dl2.glb","file_path":"3k/3kew42vdedd433vbl575xysp9dl2.glb"},"android_texture":{"id":"28414","url":"https://assets.lig.com.tw/ar_asset/3kew42vdedd433vbl575xysp9dl2.glb","file_path":"3k/3kew42vdedd433vbl575xysp9dl2.glb"}},"actions":null,"transparency":1.0,"group":1,"zone_id":42,"events":[],"scene_id":4010,"sub_events":{},"is_child":false},{"id":69152,"name":"導覽員第一層-第四區","location":{"y":-0.58725,"rotate_y":0.0,"z":0.6,"x":0.0,"rotate_x":0.0,"rotate_z":0.0},"zoom":{"x":1.0,"y":1.0,"z":1.0},"configuration":null,"created_at":"2025-10-29T03:47:12.422+08:00","updated_at":"2025-11-24T01:19:31.135+08:00","light_id":null,"ar_object_owner_id":null,"ar_object_owner_type":null,"model":{"type":5,"fields":{"width":1.0,"height":1.0,"face_me":false,"is_ignore":false,"visible_distance":20.0,"is_hidden":false,"is_size_scale_lock":true,"is_allow_pinch":false,"is_double_sided":false,"is_occlusion":false,"bloom_intensity":0.0,"bloom_radius":0.0},"texture":{"url":"https://assets.lig.com.tw/ar_asset/gywcs2kq5g367swkm8s51wig1vz4.png","id":"28496","content_type":"image/png","file_path":"gy/gywcs2kq5g367swkm8s51wig1vz4.png"},"ios_texture":{"content_type":"image/png"},"android_texture":{"content_type":"image/png"}},"actions":null,"transparency":1.0,"group":1,"zone_id":42,"events":[{"id":1,"values":{},"actions":[{"id":19,"values":{"group":1,"transparency":0.0,"delay_time":0.0,"time":0.10000000149011612}},{"id":19,"values":{"group":2,"transparency":1.0,"obj_id":69151,"delay_time":0.0,"time":0.10000000149011612}},{"id":7,"values":{"group":1,"obj_id":69381,"delay_time":0.0}},{"id":7,"values":{"group":1,"obj_id":69380,"delay_time":0.0}},{"id":7,"values":{"group":1,"obj_id":69373,"delay_time":0.0}},{"id":7,"values":{"group":1,"obj_id":69372,"delay_time":0.0}},{"id":19,"values":{"group":3,"transparency":0.0,"delay_time":0.0,"time":3.0}},{"id":19,"values":{"group":4,"transparency":0.0,"obj_id":69151,"delay_time":0.0,"time":0.10000000149011612}},{"id":19,"values":{"group":5,"transparency":1.0,"obj_id":69509,"delay_time":0.0,"time":0.10000000149011612}}]}],"scene_id":4010,"sub_events":{},"is_child":false},{"id":69151,"name":"導覽員第二層-通用","location":{"y":-0.58725,"rotate_y":0.0,"z":0.6,"x":0.0,"rotate_x":0.0,"rotate_z":0.0},"zoom":{"x":1.0,"y":1.0,"z":1.0},"configuration":null,"created_at":"2025-10-29T03:47:12.379+08:00","updated_at":"2025-11-24T01:19:31.203+08:00","light_id":null,"ar_object_owner_id":null,"ar_object_owner_type":null,"model":{"type":5,"fields":{"width":1.0,"height":1.0,"face_me":false,"is_ignore":false,"visible_distance":20.0,"is_hidden":false,"is_size_scale_lock":true,"is_allow_pinch":false,"is_double_sided":false,"is_occlusion":false,"bloom_intensity":0.0,"bloom_radius":0.0},"texture":{"url":"https://assets.lig.com.tw/ar_asset/4o662o9hbaryo7sberkvi6841f7j.png","id":"28399","content_type":"image/png","file_path":"4o/4o662o9hbaryo7sberkvi6841f7j.png"},"ios_texture":{"content_type":"image/png"},"android_texture":{"content_type":"image/png"}},"actions":null,"transparency":0.0,"group":1,"zone_id":42,"events":[],"scene_id":4010,"sub_events":{},"is_child":false},{"id":69150,"name":"AR怎麼玩_png","location":{"y":-0.71193,"rotate_y":0.0,"z":0.61503,"x":0.88179,"rotate_x":0.0,"rotate_z":0.0},"zoom":{"x":0.8068,"y":0.8068,"z":0.8068},"configuration":null,"created_at":"2025-10-29T03:47:12.354+08:00","updated_at":"2025-11-24T01:19:31.707+08:00","light_id":null,"ar_object_owner_id":null,"ar_object_owner_type":null,"model":{"type":5,"fields":{"width":1.0,"height":1.0,"face_me":false,"is_ignore":false,"visible_distance":20.0,"is_hidden":false,"is_size_scale_lock":true,"is_allow_pinch":false,"is_double_sided":false,"is_occlusion":false,"bloom_intensity":0.0,"bloom_radius":0.0},"texture":{"url":"https://assets.lig.com.tw/ar_asset/177dh8yu86tfcdkfw3b8oxdy7ja5.png","id":"28405","content_type":"image/png","file_path":"17/177dh8yu86tfcdkfw3b8oxdy7ja5.png"},"ios_texture":{"content_type":"image/png"},"android_texture":{"content_type":"image/png"}},"actions":null,"transparency":0.0,"group":1,"zone_id":42,"events":[{"id":1,"values":{},"actions":[{"id":19,"values":{"group":1,"transparency":0.0,"delay_time":0.0,"time":0.10000000149011612}},{"id":19,"values":{"group":1,"transparency":1.0,"obj_id":69171,"delay_time":0.0,"time":0.10000000149011612}}]}],"scene_id":4010,"sub_events":{},"is_child":false},{"id":69149,"name":"開啟3D地圖_png","location":{"y":-0.68141,"rotate_y":0.0,"z":0.61503,"x":-0.98512,"rotate_x":0.0,"rotate_z":0.0},"zoom":{"x":0.8068,"y":0.8068,"z":0.8068},"configuration":null,"created_at":"2025-10-29T03:47:12.327+08:00","updated_at":"2025-11-24T01:19:31.620+08:00","light_id":null,"ar_object_owner_id":null,"ar_object_owner_type":null,"model":{"type":5,"fields":{"width":1.0,"height":1.0,"face_me":false,"is_ignore":false,"visible_distance":20.0,"is_hidden":false,"is_size_scale_lock":true,"is_allow_pinch":false,"is_double_sided":false,"is_occlusion":false,"bloom_intensity":0.0,"bloom_radius":0.0},"texture":{"url":"https://assets.lig.com.tw/ar_asset/gm4y0pcfu5bckv4twqcdaktp5z2t.png","id":"28404","content_type":"image/png","file_path":"gm/gm4y0pcfu5bckv4twqcdaktp5z2t.png"},"ios_texture":{"content_type":"image/png"},"android_texture":{"content_type":"image/png"}},"actions":null,"transparency":0.0,"group":1,"zone_id":42,"events":[{"id":1,"values":{},"actions":[{"id":19,"values":{"group":1,"transparency":0.0,"delay_time":0.0,"time":0.20000000298023224}},{"id":7,"values":{"group":1,"obj_id":69199,"delay_time":0.0}},{"id":19,"values":{"group":1,"transparency":1.0,"obj_id":69173,"delay_time":0.0,"time":0.20000000298023224}},{"id":7,"values":{"group":1,"obj_id":69170,"delay_time":0.0}},{"id":19,"values":{"group":1,"transparency":1.0,"obj_id":69147,"delay_time":0.0,"time":0.20000000298023224}}]}],"scene_id":4010,"sub_events":{},"is_child":false},{"id":69148,"name":"虛擬指示桿_png","location":{"y":0.0,"rotate_y":0.0,"z":0.61503,"x":0.0,"rotate_x":0.0,"rotate_z":0.0},"zoom":{"x":0.8068,"y":0.8068,"z":0.8068},"configuration":null,"created_at":"2025-10-29T03:47:12.293+08:00","updated_at":"2025-11-24T01:19:31.270+08:00","light_id":null,"ar_object_owner_id":null,"ar_object_owner_type":null,"model":{"type":5,"fields":{"width":1.0,"height":1.0,"face_me":false,"is_ignore":false,"visible_distance":20.0,"is_hidden":false,"is_size_scale_lock":true,"is_allow_pinch":false,"is_double_sided":false,"is_occlusion":false,"bloom_intensity":0.0,"bloom_radius":0.0},"texture":{"url":"https://assets.lig.com.tw/ar_asset/c7aiv5u4pjmd0xd49ntda2wqjg25.png","id":"28403","content_type":"image/png","file_path":"c7/c7aiv5u4pjmd0xd49ntda2wqjg25.png"},"ios_texture":{"content_type":"image/png"},"android_texture":{"content_type":"image/png"}},"actions":null,"transparency":0.0,"group":1,"zone_id":42,"events":[{"id":1,"values":{},"actions":[{"id":7,"values":{"group":1,"obj_id":69202,"delay_time":0.0}},{"id":19,"values":{"group":1,"transparency":0.0,"delay_time":0.0,"time":0.10000000149011612}},{"id":19,"values":{"group":2,"transparency":1.0,"obj_id":69202,"delay_time":0.0,"time":6.25}},{"id":11,"values":{"obj_id":69202,"delay_time":0.0,"fps":24.0,"start_frame":0.0,"group":2,"end_frame":150.0}},{"id":19,"values":{"group":3,"transparency":1.0,"obj_id":69202,"delay_time":0.0,"time":120.0}},{"id":11,"values":{"obj_id":69202,"delay_time":0.0,"fps":24.0,"start_frame":160.0,"group":3,"end_frame":200.0}}]}],"scene_id":4010,"sub_events":{},"is_child":false},{"id":69147,"name":"☒_關閉3D地圖_png","location":{"y":-0.45828,"rotate_y":90.0,"z":3.87189,"x":-6.56032,"rotate_x":0.0,"rotate_z":0.0},"zoom":{"x":1.3796,"y":1.3796,"z":1.3796},"configuration":null,"created_at":"2025-10-29T03:47:12.267+08:00","updated_at":"2025-11-24T01:19:31.371+08:00","light_id":null,"ar_object_owner_id":null,"ar_object_owner_type":null,"model":{"type":5,"fields":{"width":1.0,"height":1.0,"face_me":false,"is_ignore":true,"visible_distance":20.0,"is_hidden":false,"is_size_scale_lock":true,"is_child":false,"is_allow_pinch":false,"is_double_sided":true,"is_occlusion":false,"bloom_intensity":0.0,"bloom_radius":0.0},"texture":{"url":"https://assets.lig.com.tw/ar_asset/ca5rj5e10vkfhnr9dh8put50hygb.png","id":"28402","content_type":"image/png","file_path":"ca/ca5rj5e10vkfhnr9dh8put50hygb.png"},"ios_texture":{"content_type":"image/png"},"android_texture":{"content_type":"image/png"}},"actions":null,"transparency":0.0,"group":1,"zone_id":42,"events":[{"id":1,"values":{},"actions":[{"id":9,"values":{"group":1,"obj_id":69199,"delay_time":0.0}},{"id":19,"values":{"group":1,"transparency":0.0,"obj_id":69173,"delay_time":0.0,"time":0.20000000298023224}},{"id":19,"values":{"group":1,"transparency":0.0,"obj_id":69172,"delay_time":0.0,"time":0.20000000298023224}},{"id":19,"values":{"group":1,"transparency":0.0,"obj_id":69170,"delay_time":0.0,"time":0.20000000298023224}},{"id":19,"values":{"group":1,"transparency":1.0,"obj_id":69149,"delay_time":0.0,"time":0.20000000298023224}},{"id":19,"values":{"group":2,"transparency":0.0,"delay_time":0.0,"time":0.10000000149011612}}]}],"scene_id":4010,"sub_events":{},"is_child":false}],"game_reset":false,"sc_enabled":false,"is_integrated_with_bluetooth":false,"sc_room_name":null,"sc_game_id":null,"actions":null,"credentials":null,"locale":"zh-Hant"}